{
  "book": "Standard of Excellence Book 1 (Kjos)",
  "columns": "n = exercise number; title; score = teacher score-book page; student = student-book page (only where the TOC marks a new student page)",
  "student_page_anchors": {
    "1": 6, "7": 7, "15": 8, "23": 9, "30": 10, "36": 11,
    "Balance Builder (after 41)": 12, "44": 13, "50": 14, "56": 15,
    "62": 16, "68": 17, "74": 18, "80": 19, "SAWMILL CREEK": 20,
    "MONTEGO BAY": 21, "85": 22, "92": 23, "99": 24, "107": 25,
    "112": 26, "118": 27, "123": 28, "129": 29, "Balance Builder (after 134)": 30,
    "135": 31, "138": 32, "142": 33, "147": 34, "152": 35,
    "Instrument Specific Solos": 36, "ROCKIN' RONDEAU": 38, "Excellerators": 39
  },
  "pacing_hypothesis": "She does ~1 STUDENT page/week. Student pages 6..~39 span the numbered exercises over ~34 weeks, which fits a Sep-Jun year. Real week->page pacing (breaks, concerts, review) to be derived from her period-1 agenda PDF.",
  "lines": [
    {"n": 1, "title": "Time For Band", "score": 74},
    {"n": 2, "title": "The Fun Continues", "score": 76},
    {"n": 3, "title": "Whole Lotta Counting", "score": 77},
    {"n": 4, "title": "Four Score", "score": 78},
    {"n": 5, "title": "Mix 'Em Up", "score": 80},
    {"n": 6, "title": "Melting Pot", "score": 81},
    {"n": 7, "title": "Band On Parade", "score": 82},
    {"n": 8, "title": "A Breath Of Fresh Air", "score": 84},
    {"n": 9, "title": "Side By Side", "score": 85},
    {"n": 10, "title": "Two by Two", "score": 86},
    {"n": 11, "title": "Half The Price", "score": 88},
    {"n": 12, "title": "Cardiff By The Sea", "score": 90},
    {"n": 13, "title": "Two For The Show - Duet", "score": 92},
    {"n": 14, "title": "Go For Excellence!", "score": 94, "assessment": true},
    {"quiz": "Standard of Excellence Quiz 1", "score": 95},
    {"n": 15, "title": "A Quarter's Worth", "score": 96},
    {"n": 16, "title": "Hot Cross Buns", "score": 97},
    {"n": 17, "title": "Au Claire De La Lune", "score": 99},
    {"n": 18, "title": "Down By The Station", "score": 100},
    {"n": 19, "title": "Easy Street", "score": 102},
    {"n": 20, "title": "Country Walk", "score": 104},
    {"n": 21, "title": "Gettin' It Together", "score": 105},
    {"n": 22, "title": "For ... Only", "score": 106},
    {"n": 23, "title": "Merrily We Roll Along", "score": 108},
    {"n": 24, "title": "Lightly Row - Duet", "score": 109},
    {"n": 25, "title": "One Step At A Time", "score": 110},
    {"n": 26, "title": "Good King Wenceslas", "score": 112},
    {"n": 27, "title": "Song Of The Fjords", "score": 114},
    {"n": 28, "title": "(your name) Composer", "score": 115},
    {"n": 29, "title": "Go For Excellence!", "score": 116, "assessment": true},
    {"quiz": "Standard of Excellence Quiz 2", "score": 117},
    {"n": 30, "title": "Warm-Up", "score": 118},
    {"n": 31, "title": "Tied And True", "score": 120},
    {"n": 32, "title": "Jolly Old St. Nicholas - Duet", "score": 121},
    {"n": 33, "title": "Amigos", "score": 122},
    {"n": 34, "title": "Farm Out", "score": 124},
    {"n": 35, "title": "For ... Only", "score": 126},
    {"n": 36, "title": "Mark Time", "score": 128},
    {"n": 37, "title": "Sweetly Sings The Donkey - Round", "score": 130},
    {"n": 38, "title": "Mary Ann", "score": 132},
    {"n": 39, "title": "Crusader's March", "score": 134},
    {"n": 40, "title": "Balance The Scales", "score": 136},
    {"quiz": "Standard of Excellence Quiz 3", "score": 137},
    {"n": 41, "title": "Go For Excellence!", "score": 138},
    {"special": "Balance Builder", "score": 140},
    {"special": "JINGLE BELLS - Band Arrangement", "score": 146},
    {"n": 42, "title": "School Song", "score": 146},
    {"n": 43, "title": "For ... Only", "score": 148, "assessment": true},
    {"n": 44, "title": "Warm-Up", "score": 149},
    {"n": 45, "title": "Eighth Note Encounter", "score": 150},
    {"n": 46, "title": "Jim Along Josie", "score": 151},
    {"n": 47, "title": "Eighth Note Explorer", "score": 152},
    {"n": 48, "title": "Go Tell Bill", "score": 153},
    {"quiz": "Standard of Excellence Quiz 4", "score": 155},
    {"n": 49, "title": "Go For Excellence!", "score": 156, "assessment": true},
    {"n": 50, "title": "Eighth Note Express", "score": 158},
    {"n": 51, "title": "Skip It, Lou", "score": 159},
    {"n": 52, "title": "Eighth Note Expert", "score": 161},
    {"n": 53, "title": "Mexican Mountain Song", "score": 162},
    {"n": 54, "title": "Baffling Bar Lines", "score": 164},
    {"n": 55, "title": "For ... Only", "score": 165, "assessment": true},
    {"n": 56, "title": "Warm-Up", "score": 166},
    {"n": 57, "title": "Theme From \"Symphony No. 1\"", "score": 168},
    {"n": 58, "title": "Erie Canal Capers", "score": 170},
    {"n": 59, "title": "Laughing Song - Round", "score": 172},
    {"quiz": "Standard of Excellence Quiz 5", "score": 173},
    {"n": 60, "title": "Star Search", "score": 174},
    {"n": 61, "title": "Go For Excellence!", "score": 176, "assessment": true},
    {"n": 62, "title": "Climbing Stairs", "score": 180},
    {"n": 63, "title": "Bingo", "score": 182},
    {"n": 64, "title": "There's Music In The Air", "score": 184},
    {"n": 65, "title": "There's The Same Music In The Air", "score": 185},
    {"n": 66, "title": "Scale Skill", "score": 186},
    {"n": 67, "title": "For ... Only", "score": 187},
    {"n": 68, "title": "Warm-Up", "score": 188},
    {"n": 69, "title": "Channel Three", "score": 189},
    {"n": 70, "title": "Down In The Valley", "score": 190},
    {"n": 71, "title": "Brother Martin - Round", "score": 192},
    {"n": 72, "title": "The Little Fish", "score": 194},
    {"n": 73, "title": "Go For Excellence!", "score": 196},
    {"quiz": "Standard of Excellence Quiz 6", "score": 198},
    {"n": 74, "title": "Warm-Up", "score": 199},
    {"n": 75, "title": "Old Blue", "score": 200},
    {"n": 76, "title": "Third Time Around", "score": 202},
    {"n": 77, "title": "Lullaby - Duet", "score": 204},
    {"n": 78, "title": "Minuteman March", "score": 206, "assessment": true},
    {"n": 79, "title": "For ... Only", "score": 208},
    {"n": 80, "title": "Mexican Hat Dance", "score": 210},
    {"n": 81, "title": "Frere Jacques - Round", "score": 212},
    {"n": 82, "title": "Morning Mood", "score": 214},
    {"n": 83, "title": "Ming Court", "score": 216},
    {"n": 84, "title": "Go For Excellence!", "score": 218, "assessment": true},
    {"special": "SAWMILL CREEK - Solo with Piano Accompaniment", "score": 220},
    {"special": "MONTEGO BAY - Band Arrangement", "score": 224},
    {"special": "REGAL MARCH - Band Arrangement", "score": 231},
    {"n": 85, "title": "Warm-Up", "score": 236},
    {"n": 86, "title": "Full Of Hot Air", "score": 237},
    {"n": 87, "title": "Danza Giovanni", "score": 238},
    {"n": 88, "title": "(Concert Bb) Major Scale Skill", "score": 240, "assessment": true},
    {"n": 89, "title": "The Man On The Flying Trapeze", "score": 243},
    {"n": 90, "title": "(your name) Composer", "score": 244},
    {"n": 91, "title": "For ... Only", "score": 246},
    {"n": 92, "title": "Look Sharp", "score": 248},
    {"n": 93, "title": "Aura Lee", "score": 250},
    {"n": 94, "title": "Barcarolle", "score": 252},
    {"n": 95, "title": "Just By Accident", "score": 253},
    {"n": 96, "title": "(Concert F) Major Scale Skill", "score": 254, "assessment": true},
    {"n": 97, "title": "Sailor's Song", "score": 256},
    {"n": 98, "title": "Go For Excellence!", "score": 257},
    {"quiz": "Standard of Excellence Quiz 7", "score": 258},
    {"n": 99, "title": "Warm-Up", "score": 259},
    {"n": 100, "title": "In The Pocket", "score": 260},
    {"n": 101, "title": "Pocket Change", "score": 261},
    {"n": 102, "title": "Strictly Business", "score": 262},
    {"n": 103, "title": "Smooth Sailing", "score": 263},
    {"n": 104, "title": "Roses From The South", "score": 264},
    {"n": 105, "title": "Theme From \"Hansel and Gretel\"", "score": 266},
    {"n": 106, "title": "For ... Only", "score": 268},
    {"n": 107, "title": "That's A Wrap", "score": 269},
    {"n": 108, "title": "Polly Wolly Doodle", "score": 270},
    {"n": 109, "title": "Volga Boat Song", "score": 272},
    {"n": 110, "title": "(your name) Composer", "score": 274},
    {"n": 111, "title": "Go For Excellence!", "score": 276},
    {"quiz": "Standard of Excellence Quiz 8", "score": 279},
    {"n": 112, "title": "WARM-UP - Band Arrangement", "score": 280},
    {"n": 113, "title": "Short Cut", "score": 282},
    {"n": 114, "title": "Spot The Dots", "score": 283},
    {"n": 115, "title": "All Through The Night", "score": 284},
    {"n": 116, "title": "Alouette", "score": 286},
    {"n": 117, "title": "For ... Only", "score": 288},
    {"special": "Musical Terms Review", "score": 289},
    {"n": 118, "title": "Just A Little Off The Top", "score": 290},
    {"n": 119, "title": "Top Drawer - Duet", "score": 291},
    {"n": 120, "title": "Home On The Range", "score": 292},
    {"n": 121, "title": "The Conquering Hero - Duet", "score": 294},
    {"n": 122, "title": "Go For Excellence!", "score": 296, "assessment": true},
    {"n": 123, "title": "WARM-UP - Band Arrangement", "score": 297},
    {"n": 124, "title": "High Winds Ahead", "score": 299},
    {"n": 125, "title": "Look Before You Leap", "score": 300},
    {"n": 126, "title": "(Concert Eb) Major Scale Skill", "score": 301, "assessment": true},
    {"n": 127, "title": "Variations On A Theme By Mozart", "score": 304},
    {"n": 128, "title": "For ... Only", "score": 308},
    {"n": 129, "title": "Slippery Slurs", "score": 310},
    {"n": 130, "title": "Waltz Street", "score": 311},
    {"n": 131, "title": "Theme From \"Symphony No. 9\"", "score": 312},
    {"n": 132, "title": "Ready Or Not", "score": 314},
    {"n": 133, "title": "Ach! Du Lieber Augustine", "score": 316},
    {"n": 134, "title": "Go For Excellence!", "score": 318},
    {"quiz": "Standard of Excellence Quiz 9", "score": 319},
    {"special": "Balance Builder", "score": 320},
    {"special": "TRUMPET VOLUNTARY - Band Arrangement"},
    {"n": 135, "title": "Sakura - Duet", "score": 330},
    {"n": 136, "title": "Grandfather's Whiskers", "score": 334},
    {"n": 137, "title": "Twinkle Variation", "score": 336},
    {"n": 138, "title": "Partner Songs - Duet", "score": 337, "assessment": true},
    {"n": 139, "title": "Manhattan Beach March", "score": 339},
    {"n": 140, "title": "Dynamic Decision", "score": 342},
    {"n": 141, "title": "For ... Only", "score": 343},
    {"n": 142, "title": "\"Largo\" From The New World Symphony", "score": 344},
    {"n": 143, "title": "Just Fine", "score": 346},
    {"n": 144, "title": "Chorale - Duet", "score": 348},
    {"n": 145, "title": "Tempo Time", "score": 350},
    {"n": 146, "title": "Go For Excellence!", "score": 351},
    {"n": 147, "title": "Ricochet Rock", "score": 352},
    {"n": 148, "title": "Loch Lomond", "score": 354},
    {"n": 149, "title": "Shalom, Chaverim", "score": 356},
    {"n": 150, "title": "(your name) Composer", "score": 358},
    {"n": 151, "title": "For ... Only", "score": 359},
    {"n": 152, "title": "Grandfather's Clock", "score": 360},
    {"n": 153, "title": "Kum Ba Yah", "score": 362},
    {"n": 154, "title": "Grant Us Peace - Round", "score": 364},
    {"quiz": "Standard of Excellence Quiz 10", "score": 367},
    {"n": 155, "title": "Go For Excellence!", "score": 368, "assessment": true}
  ]
}
